polyfem/__init__.py
polyfem/formatting.py
polyfem/geometry_generation.py
polyfem/poly_mesher_abstraction.py
polyfem/poly_mesher_clean.py
polyfem/poly_mesher_distance_functions.py
polyfem/poly_mesher_domain.py
polyfem/poly_mesher_main.py
polyfem/poly_mesher_visualisation.py
polyfem-1.0.0.dist-info/LICENCE.txt
polyfem-1.0.0.dist-info/METADATA
polyfem-1.0.0.dist-info/WHEEL
polyfem-1.0.0.dist-info/top_level.txt
polyfem-1.0.0.dist-info/RECORD
