Metadata-Version: 2.1
Name: polyfem
Version: 1.0.0
Summary: Meshing, but poly
Author-email: Matthew Evans <mje45@bath.ac.uk>
Maintainer-email: Matthew Evans <mje45@bath.ac.uk>
License: Copyright (c) 2024 Matthew Evans
Classifier: Programming Language :: Python :: 3.8
Classifier: Development Status :: 5 - Production/Stable
Classifier: Intended Audience :: Science/Research
Classifier: Topic :: Scientific/Engineering :: Mathematics
Requires-Python: >=3.8
License-File: LICENCE.txt
Requires-Dist: numpy >=1.18.0
Requires-Dist: matplotlib >=3.4.0
Requires-Dist: scipy >=1.4.0
Requires-Dist: setuptools >=68.0.0
Requires-Dist: shapely >=2.0.0
